{
  "Rows": {
    "RowColumnAttachedInfos": {
      "0": {
        "GridRowColumnDefinition": {
          "DesignLengthInPixel": 16.0
        }
      },
      "1": {
        "GridRowColumnDefinition": {
          "DesignLengthInPixel": 32.0,
          "Mode": 1
        }
      },
      "2": {
        "GridRowColumnDefinition": {
          "DesignLengthInPixel": 16.0
        }
      },
      "3": {
        "GridRowColumnDefinition": {
          "DesignLengthInPixel": 16.0
        }
      },
      "4": {
        "GridRowColumnDefinition": {
          "DesignLengthInPixel": 32.0
        }
      },
      "5": {
        "GridRowColumnDefinition": {
          "DesignLengthInPixel": 48.0
        }
      },
      "6": {
        "GridRowColumnDefinition": {
          "DesignLengthInPixel": 16.0
        }
      },
      "7": {
        "GridRowColumnDefinition": {
          "DesignLengthInPixel": 32.0
        }
      },
      "8": {
        "GridRowColumnDefinition": {
          "DesignLengthInPixel": 32.0
        }
      },
      "9": {
        "GridRowColumnDefinition": {
          "DesignLengthInPixel": 32.0,
          "Mode": 1
        }
      },
      "10": {
        "GridRowColumnDefinition": {
          "DesignLengthInPixel": 16.0
        }
      },
      "11": {
        "GridRowColumnDefinition": {
          "DesignLengthInPixel": 32.0
        }
      },
      "12": {
        "GridRowColumnDefinition": {
          "DesignLengthInPixel": 32.0
        }
      },
      "13": {
        "GridRowColumnDefinition": {
          "DesignLengthInPixel": 16.0
        }
      },
      "14": {
        "GridRowColumnDefinition": {
          "DesignLengthInPixel": 32.0
        }
      },
      "15": {
        "GridRowColumnDefinition": {
          "DesignLengthInPixel": 32.0
        }
      },
      "16": {
        "GridRowColumnDefinition": {
          "DesignLengthInPixel": 16.0
        }
      },
      "17": {
        "GridRowColumnDefinition": {
          "DesignLengthInPixel": 32.0
        }
      },
      "18": {
        "GridRowColumnDefinition": {
          "DesignLengthInPixel": 32.0
        }
      },
      "19": {
        "GridRowColumnDefinition": {
          "DesignLengthInPixel": 16.0
        }
      },
      "20": {
        "GridRowColumnDefinition": {
          "DesignLengthInPixel": 32.0
        }
      },
      "21": {
        "GridRowColumnDefinition": {
          "DesignLengthInPixel": 32.0
        }
      },
      "22": {
        "GridRowColumnDefinition": {
          "DesignLengthInPixel": 32.0,
          "Mode": 1
        }
      },
      "23": {
        "GridRowColumnDefinition": {
          "DesignLengthInPixel": 16.0
        }
      },
      "24": {
        "GridRowColumnDefinition": {
          "DesignLengthInPixel": 32.0,
          "Mode": 2,
          "MinLength": {
            "Unit": 1
          },
          "MaxLength": {
            "Value": 1.0
          }
        }
      },
      "25": {
        "GridRowColumnDefinition": {
          "DesignLengthInPixel": 16.0
        }
      },
      "26": {
        "GridRowColumnDefinition": {
          "DesignLengthInPixel": 16.0
        }
      },
      "27": {
        "GridRowColumnDefinition": {
          "DesignLengthInPixel": 32.0
        }
      },
      "28": {
        "GridRowColumnDefinition": {
          "DesignLengthInPixel": 16.0
        }
      }
    },
    "Count": 29,
    "DefaultSize": 32.0
  },
  "Cols": {
    "RowColumnAttachedInfos": {
      "28": {
        "GridRowColumnDefinition": {
          "DesignLengthInPixel": 160.0,
          "IsHidden": true
        }
      }
    },
    "InLogicalVisibleIndexes": [
      28
    ],
    "Count": 29
  },
  "Values": {
    "1,1": "发票填报",
    "4,2": "采购单号",
    "4,16": "入库状态",
    "7,2": "供应商",
    "7,16": "采购日期",
    "11,2": "订单总金额 ",
    "11,16": "待到票金额",
    "14,16": "本期到票金额",
    "17,2": "发票编号",
    "20,2": "备注",
    "27,18": "保存",
    "27,23": "取消"
  },
  "Formulas": {
    "12,16": "IF((C13-AC13)<=0,0,C13-AC13)"
  },
  "AttachInfos": {
    "1,1": {
      "CellType": {
        "$type": "Forguncy.UserControlPageCellType, ServerDesignerCommon",
        "UserControlPageName": "弹窗标题格式"
      }
    },
    "1,28": {
      "BindingInfo": {
        "TableName": "purchase_order",
        "ColumnName": "ID",
        "GUID": "a7ed9d65-5e30-45b3-9f4c-e506dea2f295"
      }
    },
    "5,2": {
      "BindingInfo": {
        "TableName": "purchase_order",
        "ColumnName": "purchase_order_id",
        "GUID": "9e1eba49-c26b-419b-871a-3cdfd26a511d"
      }
    },
    "5,16": {
      "BindingInfo": {
        "TableName": "purchase_order",
        "ColumnName": "in_state",
        "GUID": "b5ab3f4e-88fa-4bd9-9e47-979b01f089a3",
        "RelationBinding": {
          "RelatedTable": "state_dictionary",
          "RelatedColumn": "ID",
          "DisplayColumn": "state"
        }
      }
    },
    "5,28": {
      "BindingInfo": {
        "TableName": "purchase_order",
        "ColumnName": "ID",
        "GUID": "1bdae333-2259-45ee-8261-b4209d2f60a1"
      }
    },
    "8,2": {
      "BindingInfo": {
        "TableName": "purchase_order",
        "ColumnName": "supplier_customer_id",
        "GUID": "dca7a34c-f910-4609-be11-e6d0e827a8d9",
        "RelationBinding": {
          "RelatedTable": "supplier_customer",
          "RelatedColumn": "ID",
          "DisplayColumn": "supplier_customer_name"
        }
      }
    },
    "8,16": {
      "BindingInfo": {
        "TableName": "purchase_order",
        "ColumnName": "purchase_date",
        "GUID": "f95c5cb8-a684-4aaf-a5e7-14d45f154ac2"
      }
    },
    "12,2": {
      "BindingInfo": {
        "TableName": "purchase_order",
        "ColumnName": "total_number",
        "GUID": "ef01557b-d89a-461b-a7c7-46b5bd91a10e"
      }
    },
    "12,28": {
      "BindingInfo": {
        "TableName": "purchase_order",
        "ColumnName": "ticket_number",
        "GUID": "ee7a1b89-15a2-42ae-ba1e-a350ecc54966"
      }
    },
    "15,16": {
      "CellType": {
        "$type": "ElementUI.InputCellType, ElementUI",
        "CommandList": [],
        "UIPermissions": [
          {
            "Scope": 2,
            "AllowRoles": [
              "FGC_Anonymous"
            ]
          },
          {
            "Scope": 1,
            "AllowRoles": [
              "FGC_Anonymous"
            ]
          },
          {
            "Scope": 4,
            "AllowRoles": [
              "FGC_Anonymous"
            ]
          }
        ],
        "type": "text",
        "resize": "none"
      },
      "DataValidationInfo": {
        "NumberType": 2,
        "CompareParamType": 4,
        "FirstParamValue": "0",
        "IgnoreBlank": false,
        "ErrorMessage": "本期到票金额不能小于等于0！",
        "ErrorTo": 1,
        "ErrorToTargetCell": {
          "SerializeProperty": "=到票!Q17"
        }
      },
      "RulesGuidList": [
        "1e1bc88b-382f-4133-b453-156b263645c4"
      ]
    },
    "16,16": {
      "CellType": {
        "$type": "Forguncy.UserControlPageCellType, ServerDesignerCommon",
        "UserControlPageName": "出错警告格式"
      }
    },
    "18,2": {
      "CellType": {
        "$type": "ElementUI.InputCellType, ElementUI",
        "CommandList": [],
        "UIPermissions": [
          {
            "Scope": 2,
            "AllowRoles": [
              "FGC_Anonymous"
            ]
          },
          {
            "Scope": 1,
            "AllowRoles": [
              "FGC_Anonymous"
            ]
          },
          {
            "Scope": 4,
            "AllowRoles": [
              "FGC_Anonymous"
            ]
          }
        ],
        "type": "text",
        "resize": "none"
      },
      "DataValidationInfo": {
        "CompareParamType": 4,
        "IgnoreBlank": false,
        "ErrorMessage": "发票编号不能为空！",
        "ErrorTo": 1,
        "ErrorToTargetCell": {
          "SerializeProperty": "=到票!C20"
        }
      },
      "RulesGuidList": [
        "25bdf048-fe3e-4b94-97dd-ecc9a533f310"
      ]
    },
    "19,2": {
      "CellType": {
        "$type": "Forguncy.UserControlPageCellType, ServerDesignerCommon",
        "UserControlPageName": "出错警告格式"
      }
    },
    "21,2": {
      "CellType": {
        "$type": "ElementUI.InputCellType, ElementUI",
        "CommandList": [],
        "UIPermissions": [
          {
            "Scope": 2,
            "AllowRoles": [
              "FGC_Anonymous"
            ]
          },
          {
            "Scope": 1,
            "AllowRoles": [
              "FGC_Anonymous"
            ]
          },
          {
            "Scope": 4,
            "AllowRoles": [
              "FGC_Anonymous"
            ]
          }
        ],
        "type": "text",
        "resize": "none"
      },
      "RulesGuidList": [
        "5d6420a0-c215-4446-9348-43ce6bddad4e"
      ]
    },
    "27,18": {
      "CellType": {
        "$type": "Forguncy.ButtonCellType, ServerDesignerCommon",
        "CommandList": [
          {
            "$type": "Forguncy.Model.RequestServerCommand, ServerDesignerCommon",
            "ServerCommandName": "PurchaseInvoiceMaintenance",
            "Parameters": [
              {
                "$type": "Forguncy.Model.RequestServerCommandObjectParam, ServerDesignerCommon",
                "ParamName": "OperateType",
                "Value": "Add",
                "Remark": "操作类型，包括：Add，Update，Delete"
              },
              {
                "$type": "Forguncy.Model.RequestServerCommandObjectParam, ServerDesignerCommon",
                "ParamName": "PurchaseOrderID",
                "Value": {
                  "$type": "Forguncy.Model.FormulaReferObject, ServerDesignerCommon",
                  "SerializeProperty": "=到票!AC6"
                },
                "Remark": "采购单ID"
              },
              {
                "$type": "Forguncy.Model.RequestServerCommandObjectParam, ServerDesignerCommon",
                "ParamName": "InvoiceID",
                "Remark": "发票记录ID"
              },
              {
                "$type": "Forguncy.Model.RequestServerCommandObjectParam, ServerDesignerCommon",
                "ParamName": "InvoiceAmount",
                "Value": {
                  "$type": "Forguncy.Model.FormulaReferObject, ServerDesignerCommon",
                  "SerializeProperty": "=到票!Q16"
                },
                "Remark": "本期到票金额"
              },
              {
                "$type": "Forguncy.Model.RequestServerCommandObjectParam, ServerDesignerCommon",
                "ParamName": "InvoiceNumber",
                "Value": {
                  "$type": "Forguncy.Model.FormulaReferObject, ServerDesignerCommon",
                  "SerializeProperty": "=到票!C19"
                },
                "Remark": "发票号码"
              },
              {
                "$type": "Forguncy.Model.RequestServerCommandObjectParam, ServerDesignerCommon",
                "ParamName": "Note",
                "Value": {
                  "$type": "Forguncy.Model.FormulaReferObject, ServerDesignerCommon",
                  "SerializeProperty": "=到票!C22"
                },
                "Remark": "备注"
              }
            ],
            "ResultErrorCodeTo": {
              "SerializeProperty": "ReturnCode"
            },
            "ResultMessageTo": {
              "SerializeProperty": "ReturnMessage"
            },
            "RefreshAfterFinish": true,
            "CheckDataValidation": true
          },
          {
            "$type": "Forguncy.Model.ConditionCommand, ServerDesignerCommon",
            "ConditionAndCommandPairList": [
              {
                "Condition": {
                  "$type": "Forguncy.Model.IfCondition, ServerDesignerCommon",
                  "param": {
                    "$type": "Forguncy.Model.IfConditionPageElementParam, ServerDesignerCommon",
                    "cellLocations": [
                      {
                        "SerializeProperty": "=到票!ReturnCode"
                      }
                    ]
                  },
                  "value": "0",
                  "compareType": 1
                },
                "CommandList": [
                  {
                    "$type": "Forguncy.Model.ShareCommand, ServerDesignerCommon",
                    "ShareCommandContainerRefer": {
                      "ShareCommandContainerID": "5ce20eed-443f-4749-988e-2542c5a291ad"
                    },
                    "Params": [
                      {
                        "ParamReferObject": {
                          "ParamID": "23b3db3f-ee43-477b-838f-419a5d219a4e",
                          "ShareCommandContainerReferObject": {
                            "ShareCommandContainerID": "5ce20eed-443f-4749-988e-2542c5a291ad"
                          }
                        },
                        "Value": "操作异常",
                        "Remark": "标题内容"
                      },
                      {
                        "ParamReferObject": {
                          "ParamID": "552bab51-a087-4a1d-885b-b1df2549c039",
                          "ShareCommandContainerReferObject": {
                            "ShareCommandContainerID": "5ce20eed-443f-4749-988e-2542c5a291ad"
                          }
                        },
                        "Value": {
                          "$type": "Forguncy.Model.FormulaReferObject, ServerDesignerCommon",
                          "SerializeProperty": "=到票!ReturnMessage"
                        },
                        "Remark": "通知内容"
                      },
                      {
                        "ParamReferObject": {
                          "ParamID": "67c0173d-5e65-4382-96cd-c173611bbb69",
                          "ShareCommandContainerReferObject": {
                            "ShareCommandContainerID": "5ce20eed-443f-4749-988e-2542c5a291ad"
                          }
                        },
                        "Value": "Fail",
                        "Remark": "通知类型，包括：Success、Fail、Warning、Message"
                      }
                    ]
                  }
                ],
                "ID": "a4eddf70-9aae-4c7f-b482-0c0cd14900bf"
              },
              {
                "CommandList": [
                  {
                    "$type": "Forguncy.Model.ShareCommand, ServerDesignerCommon",
                    "ShareCommandContainerRefer": {
                      "ShareCommandContainerID": "d165caef-9315-4d99-8f90-e1a8691d34da"
                    },
                    "Params": [
                      {
                        "ParamReferObject": {
                          "ParamID": "edbc4e90-b321-4ada-a9ac-7e6ac1298c41",
                          "ShareCommandContainerReferObject": {
                            "ShareCommandContainerID": "d165caef-9315-4d99-8f90-e1a8691d34da"
                          }
                        },
                        "Value": "发票金额录入成功",
                        "Remark": "消息内容"
                      },
                      {
                        "ParamReferObject": {
                          "ParamID": "4047e995-0452-4ca2-ac6f-55deeaa966ac",
                          "ShareCommandContainerReferObject": {
                            "ShareCommandContainerID": "d165caef-9315-4d99-8f90-e1a8691d34da"
                          }
                        },
                        "Value": "Success",
                        "Remark": "消息类型，包括：Success、Fail、Warning、Message"
                      }
                    ],
                    "ReturnPropertiesTo": [
                      {
                        "ReturnPropertyReferObject": {
                          "ParamID": "43ef666c-eddd-4b90-a51f-47996a5d7b39",
                          "ShareCommandContainerReferObject": {
                            "ShareCommandContainerID": "d165caef-9315-4d99-8f90-e1a8691d34da"
                          }
                        }
                      }
                    ]
                  },
                  {
                    "$type": "Forguncy.Model.ClosePopupCommand, ServerDesignerCommon",
                    "ReloadData": true
                  }
                ],
                "ID": "3d30e66a-a3ae-41f7-ae07-2d37554bde32"
              }
            ]
          }
        ],
        "Text": "保存",
        "TemplateKey": "_RS_Main1"
      },
      "RulesGuidList": [
        "13db3626-d124-4069-ab44-4d4d95802be9"
      ]
    },
    "27,23": {
      "CellType": {
        "$type": "Forguncy.ButtonCellType, ServerDesignerCommon",
        "CommandList": [
          {
            "$type": "Forguncy.Model.ClosePopupCommand, ServerDesignerCommon"
          }
        ],
        "Text": "取消",
        "TemplateKey": "_RS_Minor1"
      }
    }
  },
  "StyleDatas": {
    "Styles": [
      {
        "FontFamily": 0
      },
      {
        "FontFamily": 0,
        "FontSize": 18.666666666666664,
        "FontWeight": 1,
        "Formatter": 2
      },
      {
        "FontFamily": 0,
        "BorderBottom": null,
        "BorderTop": null,
        "BorderLeft": null,
        "BorderRight": null
      },
      {
        "FontFamily": 0,
        "Foreground": 3,
        "Formatter": 2,
        "BorderBottom": null,
        "BorderTop": null,
        "BorderLeft": null,
        "BorderRight": null
      },
      {
        "FontFamily": 0,
        "FontSize": 16.0,
        "FontWeight": 1
      },
      {
        "FontFamily": 0,
        "FontSize": 16.0,
        "FontWeight": 1,
        "BorderBottom": null,
        "BorderTop": null,
        "BorderLeft": null,
        "BorderRight": null
      },
      {
        "FontFamily": 0,
        "WordWrap": true
      },
      {
        "FontFamily": 0,
        "Formatter": 4
      },
      {
        "FontFamily": 0,
        "Underline": true,
        "BorderBottom": null,
        "BorderTop": null,
        "BorderLeft": null,
        "BorderRight": null
      },
      {
        "FontFamily": 0,
        "Underline": true
      },
      {
        "FontFamily": 0,
        "Foreground": 3,
        "Underline": false
      },
      {
        "FontFamily": 0,
        "FontSize": 32.0,
        "FontWeight": 1,
        "Foreground": 5
      },
      {
        "FontFamily": 0,
        "Underline": false
      },
      {
        "FontFamily": 0,
        "Formatter": 2
      },
      {
        "FontFamily": 0,
        "Foreground": 3,
        "Formatter": 2,
        "Underline": false
      }
    ],
    "Types": {
      "Strs": [
        "Body",
        "Bold",
        "[AUTO]General",
        "Text 1 50",
        "yyyy\"年\"m\"月\"d\"日\";@",
        "Accent 1 0"
      ]
    },
    "CellStyles": {
      "0,0": 0,
      "0,1": 0,
      "0,2": 0,
      "0,3": 0,
      "0,4": 0,
      "0,5": 0,
      "0,6": 0,
      "0,7": 0,
      "0,8": 0,
      "0,9": 0,
      "0,10": 0,
      "0,11": 0,
      "0,12": 0,
      "0,13": 0,
      "0,14": 0,
      "0,15": 0,
      "0,16": 0,
      "0,17": 0,
      "0,18": 0,
      "0,19": 0,
      "0,20": 0,
      "0,21": 0,
      "0,22": 0,
      "0,23": 0,
      "0,24": 0,
      "0,25": 0,
      "0,26": 0,
      "0,27": 0,
      "0,28": 0,
      "1,0": 0,
      "1,1": 1,
      "1,27": 2,
      "1,28": 0,
      "2,0": 0,
      "2,1": 2,
      "2,2": 2,
      "2,3": 2,
      "2,4": 2,
      "2,5": 2,
      "2,6": 2,
      "2,7": 2,
      "2,8": 2,
      "2,9": 2,
      "2,10": 2,
      "2,11": 2,
      "2,12": 2,
      "2,13": 2,
      "2,14": 2,
      "2,15": 2,
      "2,16": 2,
      "2,17": 2,
      "2,18": 2,
      "2,19": 2,
      "2,20": 2,
      "2,21": 2,
      "2,22": 2,
      "2,23": 2,
      "2,24": 2,
      "2,25": 2,
      "2,26": 2,
      "2,27": 2,
      "2,28": 0,
      "3,0": 0,
      "3,1": 2,
      "3,2": 2,
      "3,3": 2,
      "3,4": 2,
      "3,5": 2,
      "3,6": 2,
      "3,7": 2,
      "3,8": 2,
      "3,9": 2,
      "3,10": 2,
      "3,11": 2,
      "3,12": 2,
      "3,13": 2,
      "3,14": 2,
      "3,15": 2,
      "3,16": 2,
      "3,17": 2,
      "3,18": 2,
      "3,19": 2,
      "3,20": 2,
      "3,21": 2,
      "3,22": 2,
      "3,23": 2,
      "3,24": 2,
      "3,25": 2,
      "3,26": 2,
      "3,27": 2,
      "3,28": 0,
      "4,0": 0,
      "4,1": 2,
      "4,2": 3,
      "4,3": 2,
      "4,4": 2,
      "4,5": 2,
      "4,6": 2,
      "4,7": 2,
      "4,8": 2,
      "4,9": 2,
      "4,10": 2,
      "4,11": 2,
      "4,12": 2,
      "4,13": 2,
      "4,14": 2,
      "4,15": 2,
      "4,16": 3,
      "4,17": 2,
      "4,18": 2,
      "4,19": 2,
      "4,20": 2,
      "4,21": 2,
      "4,22": 2,
      "4,23": 2,
      "4,24": 2,
      "4,25": 2,
      "4,26": 2,
      "4,27": 0,
      "4,28": 0,
      "5,0": 0,
      "5,1": 2,
      "5,2": 4,
      "5,3": 0,
      "5,4": 0,
      "5,5": 0,
      "5,6": 0,
      "5,7": 0,
      "5,8": 0,
      "5,9": 0,
      "5,10": 0,
      "5,11": 0,
      "5,12": 0,
      "5,13": 0,
      "5,14": 0,
      "5,15": 2,
      "5,16": 4,
      "5,17": 0,
      "5,18": 0,
      "5,19": 0,
      "5,20": 0,
      "5,21": 0,
      "5,22": 0,
      "5,23": 0,
      "5,24": 0,
      "5,25": 0,
      "5,26": 0,
      "5,27": 2,
      "5,28": 0,
      "6,0": 0,
      "6,1": 2,
      "6,2": 5,
      "6,3": 5,
      "6,4": 5,
      "6,5": 5,
      "6,6": 5,
      "6,7": 5,
      "6,8": 5,
      "6,9": 5,
      "6,10": 5,
      "6,11": 5,
      "6,12": 5,
      "6,13": 5,
      "6,14": 5,
      "6,15": 5,
      "6,16": 5,
      "6,17": 5,
      "6,18": 5,
      "6,19": 5,
      "6,20": 5,
      "6,21": 5,
      "6,22": 5,
      "6,23": 2,
      "6,24": 2,
      "6,25": 2,
      "6,26": 2,
      "6,27": 2,
      "6,28": 0,
      "7,0": 0,
      "7,1": 2,
      "7,2": 3,
      "7,3": 2,
      "7,4": 2,
      "7,5": 2,
      "7,6": 2,
      "7,7": 2,
      "7,8": 2,
      "7,9": 2,
      "7,10": 2,
      "7,11": 2,
      "7,12": 2,
      "7,13": 2,
      "7,14": 2,
      "7,15": 2,
      "7,16": 3,
      "7,17": 2,
      "7,18": 2,
      "7,19": 2,
      "7,20": 2,
      "7,21": 2,
      "7,22": 2,
      "7,23": 2,
      "7,24": 2,
      "7,25": 2,
      "7,26": 2,
      "7,27": 2,
      "7,28": 0,
      "8,0": 0,
      "8,1": 2,
      "8,2": 6,
      "8,15": 2,
      "8,16": 7,
      "8,17": 0,
      "8,18": 0,
      "8,19": 0,
      "8,20": 0,
      "8,21": 0,
      "8,22": 0,
      "8,23": 0,
      "8,24": 0,
      "8,25": 0,
      "8,26": 0,
      "8,27": 2,
      "8,28": 0,
      "9,0": 0,
      "9,1": 0,
      "9,15": 0,
      "9,16": 0,
      "9,17": 0,
      "9,18": 0,
      "9,19": 0,
      "9,20": 0,
      "9,21": 0,
      "9,22": 0,
      "9,23": 0,
      "9,24": 0,
      "9,25": 0,
      "9,26": 0,
      "9,27": 0,
      "9,28": 0,
      "10,0": 0,
      "10,1": 2,
      "10,2": 8,
      "10,3": 8,
      "10,4": 8,
      "10,5": 8,
      "10,6": 8,
      "10,7": 8,
      "10,8": 8,
      "10,9": 8,
      "10,10": 8,
      "10,11": 8,
      "10,12": 8,
      "10,13": 8,
      "10,14": 8,
      "10,15": 8,
      "10,16": 8,
      "10,17": 8,
      "10,18": 8,
      "10,19": 8,
      "10,20": 8,
      "10,21": 8,
      "10,22": 8,
      "10,23": 2,
      "10,24": 2,
      "10,25": 2,
      "10,26": 2,
      "10,27": 2,
      "10,28": 0,
      "11,0": 0,
      "11,1": 0,
      "11,2": 3,
      "11,3": 2,
      "11,4": 2,
      "11,5": 2,
      "11,6": 2,
      "11,7": 2,
      "11,8": 2,
      "11,9": 2,
      "11,10": 2,
      "11,11": 2,
      "11,12": 2,
      "11,13": 2,
      "11,14": 2,
      "11,15": 9,
      "11,16": 10,
      "11,17": 9,
      "11,18": 9,
      "11,19": 9,
      "11,20": 9,
      "11,21": 9,
      "11,22": 9,
      "11,23": 0,
      "11,24": 0,
      "11,25": 0,
      "11,26": 0,
      "11,27": 0,
      "11,28": 0,
      "12,0": 0,
      "12,1": 0,
      "12,2": 11,
      "12,3": 0,
      "12,4": 0,
      "12,5": 0,
      "12,6": 0,
      "12,7": 0,
      "12,8": 0,
      "12,9": 0,
      "12,10": 0,
      "12,11": 0,
      "12,12": 0,
      "12,13": 0,
      "12,14": 0,
      "12,15": 9,
      "12,16": 12,
      "12,17": 0,
      "12,18": 0,
      "12,19": 0,
      "12,20": 0,
      "12,21": 0,
      "12,22": 0,
      "12,23": 0,
      "12,24": 0,
      "12,25": 0,
      "12,26": 0,
      "12,27": 0,
      "12,28": 0,
      "13,0": 0,
      "13,1": 0,
      "13,2": 0,
      "13,3": 0,
      "13,4": 0,
      "13,5": 0,
      "13,6": 0,
      "13,7": 0,
      "13,8": 0,
      "13,9": 0,
      "13,10": 0,
      "13,11": 0,
      "13,12": 0,
      "13,13": 0,
      "13,14": 0,
      "13,15": 9,
      "13,16": 9,
      "13,17": 9,
      "13,18": 9,
      "13,19": 9,
      "13,20": 9,
      "13,21": 9,
      "13,22": 9,
      "13,23": 0,
      "13,24": 0,
      "13,25": 0,
      "13,26": 0,
      "13,27": 0,
      "13,28": 0,
      "14,0": 0,
      "14,1": 0,
      "14,2": 0,
      "14,3": 0,
      "14,4": 0,
      "14,5": 0,
      "14,6": 0,
      "14,7": 0,
      "14,8": 0,
      "14,9": 0,
      "14,10": 0,
      "14,11": 0,
      "14,12": 0,
      "14,13": 0,
      "14,14": 0,
      "14,15": 9,
      "14,16": 10,
      "14,17": 9,
      "14,18": 9,
      "14,19": 9,
      "14,20": 9,
      "14,21": 9,
      "14,22": 9,
      "14,23": 0,
      "14,24": 0,
      "14,25": 0,
      "14,26": 0,
      "14,27": 0,
      "14,28": 0,
      "15,0": 0,
      "15,1": 0,
      "15,2": 0,
      "15,3": 0,
      "15,4": 0,
      "15,5": 0,
      "15,6": 0,
      "15,7": 0,
      "15,8": 0,
      "15,9": 0,
      "15,10": 0,
      "15,11": 0,
      "15,12": 0,
      "15,13": 0,
      "15,14": 0,
      "15,15": 9,
      "15,16": 12,
      "15,27": 0,
      "16,0": 0,
      "16,1": 0,
      "16,2": 9,
      "16,3": 9,
      "16,4": 9,
      "16,5": 9,
      "16,6": 9,
      "16,7": 9,
      "16,8": 9,
      "16,9": 9,
      "16,10": 9,
      "16,11": 9,
      "16,12": 9,
      "16,13": 9,
      "16,14": 9,
      "16,15": 9,
      "16,16": 13,
      "16,27": 0,
      "16,28": 0,
      "17,0": 0,
      "17,1": 0,
      "17,2": 14,
      "17,3": 9,
      "17,4": 9,
      "17,5": 9,
      "17,6": 9,
      "17,7": 9,
      "17,8": 9,
      "17,9": 0,
      "17,10": 0,
      "17,11": 0,
      "17,12": 0,
      "17,13": 9,
      "17,14": 9,
      "17,15": 9,
      "17,16": 9,
      "17,17": 9,
      "17,18": 9,
      "17,19": 9,
      "17,20": 9,
      "17,21": 9,
      "17,22": 9,
      "17,23": 0,
      "17,24": 0,
      "17,25": 0,
      "17,26": 0,
      "17,27": 0,
      "17,28": 0,
      "18,0": 0,
      "18,1": 0,
      "18,2": 12,
      "18,27": 0,
      "19,0": 0,
      "19,1": 0,
      "19,2": 13,
      "19,27": 0,
      "19,28": 0,
      "20,0": 0,
      "20,1": 2,
      "20,2": 3,
      "20,3": 2,
      "20,4": 2,
      "20,5": 2,
      "20,6": 2,
      "20,7": 2,
      "20,8": 2,
      "20,9": 2,
      "20,10": 2,
      "20,11": 2,
      "20,12": 2,
      "20,13": 2,
      "20,14": 2,
      "20,15": 2,
      "20,16": 2,
      "20,17": 2,
      "20,18": 2,
      "20,19": 2,
      "20,20": 2,
      "20,21": 2,
      "20,22": 2,
      "20,23": 2,
      "20,24": 2,
      "20,25": 2,
      "20,26": 2,
      "20,27": 2,
      "20,28": 0,
      "21,0": 0,
      "21,1": 2,
      "21,2": 6,
      "21,27": 2,
      "21,28": 0,
      "22,0": 0,
      "22,1": 2,
      "22,27": 2,
      "22,28": 0,
      "23,0": 0,
      "23,1": 0,
      "23,2": 0,
      "23,3": 0,
      "23,4": 0,
      "23,5": 0,
      "23,6": 0,
      "23,7": 0,
      "23,8": 0,
      "23,9": 0,
      "23,10": 0,
      "23,11": 0,
      "23,12": 0,
      "23,13": 0,
      "23,14": 0,
      "23,15": 0,
      "23,16": 0,
      "23,17": 0,
      "23,18": 0,
      "23,19": 0,
      "23,20": 0,
      "23,21": 0,
      "23,22": 0,
      "23,23": 0,
      "23,24": 0,
      "23,25": 0,
      "23,26": 0,
      "23,27": 0,
      "23,28": 0,
      "24,0": 0,
      "24,1": 0,
      "24,2": 0,
      "24,3": 0,
      "24,4": 0,
      "24,5": 0,
      "24,6": 0,
      "24,7": 0,
      "24,8": 0,
      "24,9": 0,
      "24,10": 0,
      "24,11": 0,
      "24,12": 0,
      "24,13": 0,
      "24,14": 0,
      "24,15": 0,
      "24,16": 0,
      "24,17": 0,
      "24,18": 0,
      "24,19": 0,
      "24,20": 0,
      "24,21": 0,
      "24,22": 0,
      "24,23": 0,
      "24,24": 0,
      "24,25": 0,
      "24,26": 0,
      "24,27": 0,
      "24,28": 0,
      "25,0": 0,
      "25,1": 0,
      "25,2": 0,
      "25,3": 0,
      "25,4": 0,
      "25,5": 0,
      "25,6": 0,
      "25,7": 0,
      "25,8": 0,
      "25,9": 0,
      "25,10": 0,
      "25,11": 0,
      "25,12": 0,
      "25,13": 0,
      "25,14": 0,
      "25,15": 0,
      "25,16": 0,
      "25,17": 0,
      "25,18": 0,
      "25,19": 0,
      "25,20": 0,
      "25,21": 0,
      "25,22": 0,
      "25,23": 0,
      "25,24": 0,
      "25,25": 0,
      "25,26": 0,
      "25,27": 0,
      "25,28": 0,
      "26,0": 0,
      "26,1": 0,
      "26,2": 0,
      "26,3": 0,
      "26,4": 0,
      "26,5": 0,
      "26,6": 0,
      "26,7": 0,
      "26,8": 0,
      "26,9": 0,
      "26,10": 0,
      "26,11": 0,
      "26,12": 0,
      "26,13": 0,
      "26,14": 0,
      "26,15": 0,
      "26,16": 0,
      "26,17": 0,
      "26,18": 0,
      "26,19": 0,
      "26,20": 0,
      "26,21": 0,
      "26,22": 0,
      "26,23": 0,
      "26,24": 0,
      "26,25": 0,
      "26,26": 0,
      "26,27": 0,
      "26,28": 0,
      "27,0": 0,
      "27,1": 0,
      "27,2": 0,
      "27,3": 0,
      "27,4": 0,
      "27,5": 0,
      "27,6": 0,
      "27,7": 0,
      "27,8": 0,
      "27,9": 0,
      "27,10": 0,
      "27,11": 0,
      "27,12": 0,
      "27,13": 0,
      "27,14": 0,
      "27,15": 0,
      "27,16": 0,
      "27,17": 0,
      "27,18": 13,
      "27,19": 0,
      "27,20": 0,
      "27,21": 0,
      "27,22": 0,
      "27,23": 0,
      "27,24": 0,
      "27,25": 0,
      "27,26": 0,
      "27,27": 0,
      "27,28": 0,
      "28,0": 0,
      "28,1": 0,
      "28,2": 0,
      "28,3": 0,
      "28,4": 0,
      "28,5": 0,
      "28,6": 0,
      "28,7": 0,
      "28,8": 0,
      "28,9": 0,
      "28,10": 0,
      "28,11": 0,
      "28,12": 0,
      "28,13": 0,
      "28,14": 0,
      "28,15": 0,
      "28,16": 0,
      "28,17": 0,
      "28,18": 0,
      "28,19": 0,
      "28,20": 0,
      "28,21": 0,
      "28,22": 0,
      "28,23": 0,
      "28,24": 0,
      "28,25": 0,
      "28,26": 0,
      "28,27": 0,
      "28,28": 0
    },
    "SheetStyle": {
      "FontFamily": 0
    }
  },
  "Spans": [
    "5,2,1,13",
    "5,16,1,11",
    "8,16,2,11",
    "12,2,4,13",
    "12,16,1,11",
    "8,2,2,13",
    "27,23,1,4",
    "27,18,1,4",
    "15,16,1,11",
    "21,2,2,25",
    "18,2,1,25",
    "1,1,1,26",
    "16,16,1,11",
    "19,2,1,25"
  ],
  "PageInfo": {
    "$type": "Forguncy.Model.Pages.NormalPage, ServerDesignerCommon",
    "PermissionData": {
      "$type": "Forguncy.RbacPermission.Core.Impl.Page.PagePermissionData, Forguncy.RbacPermission.Core",
      "permissionResource": {
        "$type": "Forguncy.RbacPermission.Core.Impl.Page.PagePermissionResource, Forguncy.RbacPermission.Core"
      },
      "permissionBindings": [
        {
          "$type": "Forguncy.RbacPermission.Core.Impl.Page.PagePermissionBinding, Forguncy.RbacPermission.Core",
          "roleNames": [
            "Administrator",
            "采购员",
            "采购主管",
            "FGC_LoginUser"
          ]
        }
      ]
    },
    "RowBreakLines": [],
    "RepeatRangeSettings": [],
    "RelatedDataTableName": "purchase_order",
    "ConditionFormatRulesCollection": {
      "Rules": [
        {
          "$type": "Forguncy.ConditionFormat.FormulaRule, ServerDesignerCommon",
          "Formula": {
            "$type": "Forguncy.Model.FormulaReferObject, ServerDesignerCommon",
            "SerializeProperty": "=到票!$Q$13=0"
          },
          "GUID": "1e1bc88b-382f-4133-b453-156b263645c4",
          "StyleInfo": {
            "Underline": null,
            "Strikethrough": null
          },
          "IsDisabled": true
        },
        {
          "$type": "Forguncy.ConditionFormat.FormulaRule, ServerDesignerCommon",
          "Formula": {
            "$type": "Forguncy.Model.FormulaReferObject, ServerDesignerCommon",
            "SerializeProperty": "=到票!$Q$13=0"
          },
          "Priority": 1,
          "GUID": "5d6420a0-c215-4446-9348-43ce6bddad4e",
          "StyleInfo": {
            "Underline": null,
            "Strikethrough": null
          },
          "IsDisabled": true
        },
        {
          "$type": "Forguncy.ConditionFormat.FormulaRule, ServerDesignerCommon",
          "Formula": {
            "$type": "Forguncy.Model.FormulaReferObject, ServerDesignerCommon",
            "SerializeProperty": "=到票!$Q$13=0"
          },
          "Priority": 2,
          "GUID": "13db3626-d124-4069-ab44-4d4d95802be9",
          "StyleInfo": {
            "Underline": null,
            "Strikethrough": null
          },
          "IsInvisible": true
        },
        {
          "$type": "Forguncy.ConditionFormat.FormulaRule, ServerDesignerCommon",
          "Formula": {
            "$type": "Forguncy.Model.FormulaReferObject, ServerDesignerCommon",
            "SerializeProperty": "=到票!$Q$13=0"
          },
          "GUID": "25bdf048-fe3e-4b94-97dd-ecc9a533f310",
          "StyleInfo": {
            "Underline": null,
            "Strikethrough": null
          },
          "IsDisabled": true
        }
      ]
    }
  },
  "PrintInfo": {
    "PaperSize": {},
    "Margin": {}
  }
}//VVbkjPIhYHx3kh3mCV3wvcc71ga/JKnLul/xY3L1HbYbgkTSG0MPI2XTSvO7c8sQjna1BdYGOKsbaCOKkHqOXJ/AZDK2b+SGDW3EdZlK1HgYvJGZtZkIKh20iykbZTv9PPIw4y6mpLw3KEwrrAOduRdN3t+ogQhLTsbtVxh2TOCpQMmZyYrpdx2FvZ/iU2/7Clax3Yyw/bAmOGAmpObGeYKL0+dB6ocOT320d06cBYN55mPBmhjEzHwBbHCDsc1s1lL1ODUHe6L00lsKYN3oLY8ySHb7ljo+saLvunu1zZBdVnUrIEOSxSj30r+46bZH8v0EFcMkKpRRQoSR0zNNsKJjccVy5rsnf+6iHnZnFz4OV32I3mmYYWtuolbAidYurg74m4KHwqq6FEhbmsAxJVLHQ5IfYstb8QLGvWTQN/dIvabOJz50eazE3dP3aK+hw8iVObwtjQkju54isLwlMuWVHViO0XSditxZXEQhmrTVet6feaC5KBznZdOV/SR23GL5ECKjj/3tumm39h+H/IfQHj3crQgFWswbqDN1NI3iCeO5mQObg3PJuV2cYRIB1S7/lJv+20NtwUmCnxs6lVuv1qLfBwpMxju4wm40piWv45abLN52aegKU93SoqpDZPdVuZvQDIjp3frBl8WDMeyHxtHxfJnlbxU8Y/O/mTUgsHwbFkzwCzp+iqe1ogp0mq7dYgIT2ztHjHWF+8wcdNEGaWcwDtCipDhGCsWZWOwFi+WM7QjiHOW7hXzxHsO01kNJIHBWlBMy9WoMuVD+bKsp7bY07rTUT1XWsy0xDty40/rPdX2+XBc3quE6eRQj3mRfNfR8ESiaeKMLyo1c8MJVAqEDHYRtGx82VF4yV6QC55G/unMkXRSkJUGAJe6T9K/r7smh7InNgTXTRpsNLw==|920